pulse_transitions/__init__.py
pulse_transitions/common.py
pulse_transitions/impl.py
pulse_transitions/matpulse.py
pulse_transitions/transient_response.py
pulse_transitions-0.1.0.dist-info/licenses/LICENSE
pulse_transitions-0.1.0.dist-info/METADATA
pulse_transitions-0.1.0.dist-info/WHEEL
pulse_transitions-0.1.0.dist-info/top_level.txt
pulse_transitions-0.1.0.dist-info/RECORD
