Metadata-Version: 2.4
Name: pulse_transitions
Version: 0.1.0
Summary: Description
Author-email: Simon Hobbs <simon.hobbs@electrooptical.net>
License:                   GNU LESSER GENERAL PUBLIC LICENSE
Project-URL: github, https://github.com/snhobbs/pulse_transitions
Classifier: Development Status :: 2 - Pre-Alpha
Classifier: Intended Audience :: Developers
Classifier: Natural Language :: English
Classifier: Programming Language :: Python :: 3
Classifier: Programming Language :: Python :: 3.8
Classifier: Programming Language :: Python :: 3.9
Classifier: Programming Language :: Python :: 3.10
Classifier: Programming Language :: Python :: 3.11
Classifier: Programming Language :: Python :: 3.12
Classifier: Programming Language :: Python :: 3.13
Requires-Python: >=3.8
License-File: LICENSE
Requires-Dist: pandas
Requires-Dist: numpy
Requires-Dist: scipy
Requires-Dist: pydantic
Dynamic: license-file
